oold/__init__.py
oold/generator.py
oold/static.py
oold/backend/__init__.py
oold/backend/auth.py
oold/backend/document_store.py
oold/backend/interface.py
oold/backend/sparql.py
oold/drafts/field_extras.py
oold/drafts/ldc_generator.py
oold/drafts/magic_field.py
oold/model/__init__.py
oold/model/v1/__init__.py
oold/ui/__init__.py
oold/ui/anywidget/JsonEditorWidget.ipynb
oold/ui/anywidget/__init__.py
oold/ui/anywidget/jsoneditor.py
oold/ui/nicegui/__init__.py
oold/ui/nicegui/jsoneditor.py
oold/ui/nicegui/main.py
oold/ui/panel/__init__.py
oold/ui/panel/demo.py
oold/ui/panel/anywidget_vite/jsoneditor.py
oold/ui/vue/README.md
oold/ui/vue/package-lock.json
oold/ui/vue/package.json
oold/ui/vue/vite.config.anywidget.mjs
oold/ui/vue/vite.config.js
oold/ui/vue/vite.config.nicegui.js
oold/ui/vue/dist/anywidget/jsoneditor_vue.css
oold/ui/vue/dist/anywidget/jsoneditor_vue.mjs
oold/ui/vue/dist/default/jsoneditor_vue.css
oold/ui/vue/dist/default/jsoneditor_vue.mjs
oold/ui/vue/dist/nicegui/jsoneditor_vue.mjs
oold/ui/vue/src/jsoneditor.vue
oold/ui/vue/src/jsoneditor_component.js
oold/ui/vue/src/jsoneditor_component.less
oold/utils/codegen.py
oold/utils/environment.py
oold/utils/transform.py
oold-0.11.4.dist-info/licenses/LICENSE
oold-0.11.4.dist-info/METADATA
oold-0.11.4.dist-info/WHEEL
oold-0.11.4.dist-info/top_level.txt
oold-0.11.4.dist-info/RECORD
