Metadata-Version: 2.4
Name: oold
Version: 0.11.4
Summary: Linked data class python package
Home-page: https://github.com/OpenSemanticWorld/oold-python
Author: OpenSemanticWorld
Author-email: team@opensemantic.world
License: Apache 2.0
Project-URL: Documentation, https://opensemanticworld.github.io/oold-python/
Project-URL: Source, https://github.com/OpenSemanticWorld/oold-python
Project-URL: Download, https://pypi.org/project/oold/#files
Platform: any
Classifier: Development Status :: 3 - Alpha
Classifier: Programming Language :: Python
Requires-Python: >=3.10
License-File: LICENSE
Requires-Dist: importlib-metadata; python_version < "3.8"
Requires-Dist: pydantic>=2.0.0
Requires-Dist: datamodel-code-generator>=0.51.0
Requires-Dist: typing_extensions
Requires-Dist: pyld
Requires-Dist: rdflib
Requires-Dist: sparqlwrapper
Requires-Dist: jsondiff
Requires-Dist: pyyaml
Provides-Extra: ui-panel
Requires-Dist: panel; extra == "ui-panel"
Requires-Dist: jupyter_bokeh; extra == "ui-panel"
Provides-Extra: ui-jupyter
Requires-Dist: anywidget; extra == "ui-jupyter"
Requires-Dist: ipykernel; extra == "ui-jupyter"
Provides-Extra: ui-nicegui
Requires-Dist: nicegui; extra == "ui-nicegui"
Provides-Extra: ui
Requires-Dist: panel; extra == "ui"
Requires-Dist: jupyter_bokeh; extra == "ui"
Requires-Dist: anywidget; extra == "ui"
Requires-Dist: ipykernel; extra == "ui"
Requires-Dist: nicegui; extra == "ui"
Provides-Extra: all
Requires-Dist: panel; extra == "all"
Requires-Dist: jupyter_bokeh; extra == "all"
Requires-Dist: anywidget; extra == "all"
Requires-Dist: ipykernel; extra == "all"
Requires-Dist: nicegui; extra == "all"
Provides-Extra: dev
Requires-Dist: tox; extra == "dev"
Requires-Dist: pre-commit; extra == "dev"
Provides-Extra: testing
Requires-Dist: setuptools; extra == "testing"
Requires-Dist: pytest; extra == "testing"
Requires-Dist: pytest-cov; extra == "testing"
Requires-Dist: pytest-playwright; extra == "testing"
Requires-Dist: panel; extra == "testing"
Requires-Dist: jsondiff; extra == "testing"
Dynamic: license-file
